Metadata-Version: 1.0
Name: XStatic-QUnit
Version: 1.14.0.1
Summary: QUnit 1.14.0 (XStatic packaging standard)
Home-page: http://qunitjs.com
Author: Radomir Dopieralski
Author-email: openstack@sheep.art.pl
License: (same as QUnit)
Keywords: qunit xstatic
Platform: any
